[{"@context":"http:\/\/localhost\/omeka-s-3.2.3\/omeka-s\/api-context","@id":"http:\/\/localhost\/omeka-s-3.2.3\/omeka-s\/api\/items\/11","@type":["o:Item","mco:Laboratoire"],"o:id":11,"o:is_public":true,"o:owner":{"@id":"http:\/\/localhost\/omeka-s-3.2.3\/omeka-s\/api\/users\/1","o:id":1},"o:resource_class":{"@id":"http:\/\/localhost\/omeka-s-3.2.3\/omeka-s\/api\/resource_classes\/139","o:id":139},"o:resource_template":{"@id":"http:\/\/localhost\/omeka-s-3.2.3\/omeka-s\/api\/resource_templates\/15","o:id":15},"o:thumbnail":null,"o:title":"Laboratoire de recherche univ P8","thumbnail_display_urls":{"large":null,"medium":null,"square":null},"o:created":{"@value":"2022-12-05T10:06:27+00:00","@type":"http:\/\/www.w3.org\/2001\/XMLSchema#dateTime"},"o:modified":{"@value":"2022-12-05T10:06:27+00:00","@type":"http:\/\/www.w3.org\/2001\/XMLSchema#dateTime"},"o:media":[],"o:item_set":[],"o:site":[],"mco:AcommeAdress":[{"type":"literal","property_id":224,"property_label":"AcommeAdress","is_public":true,"@value":"Saint Denis, 93000"}],"mco:AcommeNom":[{"type":"literal","property_id":220,"property_label":"AcommeNom","is_public":true,"@value":"Laboratoire de recherche univ P8"}],"mco:AcommeDomaine":[{"type":"literal","property_id":225,"property_label":"AcommeDomaine","is_public":true,"@value":"Inform"}],"dcterms:title":[{"type":"literal","property_id":1,"property_label":"Title","is_public":true,"@value":"Laboratoire de recherche univ P8"}],"@reverse":{"mco:AcommeLaboratoire":[{"@id":"http:\/\/localhost\/omeka-s-3.2.3\/omeka-s\/api\/resources\/12","o:title":"Akram Imed"}]}},{"@context":"http:\/\/localhost\/omeka-s-3.2.3\/omeka-s\/api-context","@id":"http:\/\/localhost\/omeka-s-3.2.3\/omeka-s\/api\/items\/12","@type":["o:Item","mco:Chercheur"],"o:id":12,"o:is_public":true,"o:owner":{"@id":"http:\/\/localhost\/omeka-s-3.2.3\/omeka-s\/api\/users\/1","o:id":1},"o:resource_class":{"@id":"http:\/\/localhost\/omeka-s-3.2.3\/omeka-s\/api\/resource_classes\/136","o:id":136},"o:resource_template":{"@id":"http:\/\/localhost\/omeka-s-3.2.3\/omeka-s\/api\/resource_templates\/14","o:id":14},"o:thumbnail":null,"o:title":"Akram Imed","thumbnail_display_urls":{"large":null,"medium":null,"square":null},"o:created":{"@value":"2022-12-05T10:07:29+00:00","@type":"http:\/\/www.w3.org\/2001\/XMLSchema#dateTime"},"o:modified":{"@value":"2022-12-05T10:07:29+00:00","@type":"http:\/\/www.w3.org\/2001\/XMLSchema#dateTime"},"o:media":[],"o:item_set":[],"o:site":[],"mco:AcommeNom":[{"type":"literal","property_id":220,"property_label":"AcommeNom","is_public":true,"@value":"Akram Imed"}],"mco:AcommeLaboratoire":[{"type":"resource","property_id":223,"property_label":"AcommeLaboratoire","is_public":true,"@id":"http:\/\/localhost\/omeka-s-3.2.3\/omeka-s\/api\/items\/11","value_resource_id":11,"value_resource_name":"items","url":null,"display_title":"Laboratoire de recherche univ P8"}],"mco:AcommeAdress":[{"type":"literal","property_id":224,"property_label":"AcommeAdress","is_public":true,"@value":"75000,Paris"}],"dcterms:title":[{"type":"literal","property_id":1,"property_label":"Title","is_public":true,"@value":"Akram Imed"}],"@reverse":{"mco:CreePar":[{"@id":"http:\/\/localhost\/omeka-s-3.2.3\/omeka-s\/api\/resources\/13","o:title":"la blockchain dans l\u0027economie"}]}},{"@context":"http:\/\/localhost\/omeka-s-3.2.3\/omeka-s\/api-context","@id":"http:\/\/localhost\/omeka-s-3.2.3\/omeka-s\/api\/items\/13","@type":["o:Item","mco:Publication"],"o:id":13,"o:is_public":true,"o:owner":{"@id":"http:\/\/localhost\/omeka-s-3.2.3\/omeka-s\/api\/users\/1","o:id":1},"o:resource_class":{"@id":"http:\/\/localhost\/omeka-s-3.2.3\/omeka-s\/api\/resource_classes\/138","o:id":138},"o:resource_template":{"@id":"http:\/\/localhost\/omeka-s-3.2.3\/omeka-s\/api\/resource_templates\/17","o:id":17},"o:thumbnail":null,"o:title":"la blockchain dans l\u0027economie","thumbnail_display_urls":{"large":null,"medium":null,"square":null},"o:created":{"@value":"2022-12-05T10:08:36+00:00","@type":"http:\/\/www.w3.org\/2001\/XMLSchema#dateTime"},"o:modified":{"@value":"2022-12-05T10:08:36+00:00","@type":"http:\/\/www.w3.org\/2001\/XMLSchema#dateTime"},"o:media":[],"o:item_set":[],"o:site":[],"mco:AcommeUniversite":[{"type":"literal","property_id":222,"property_label":"EstSortie","is_public":true,"@value":"10\/10\/2022"}],"mco:CreePar":[{"type":"resource","property_id":221,"property_label":"CreePar","is_public":true,"@id":"http:\/\/localhost\/omeka-s-3.2.3\/omeka-s\/api\/items\/12","value_resource_id":12,"value_resource_name":"items","url":null,"display_title":"Akram Imed"}],"mco:AcommeNom":[{"type":"literal","property_id":220,"property_label":"AcommeNom","is_public":true,"@value":"la blockchain dans l\u0027economie"}],"dcterms:title":[{"type":"literal","property_id":1,"property_label":"Title","is_public":true,"@value":"la blockchain dans l\u0027economie"}]}]